jumpstarter/__init__.py
jumpstarter/py.typed
jumpstarter/client/__init__.py
jumpstarter/client/adapters.py
jumpstarter/client/base.py
jumpstarter/client/client.py
jumpstarter/client/core.py
jumpstarter/client/decorators.py
jumpstarter/client/exceptions.py
jumpstarter/client/grpc.py
jumpstarter/client/grpc_test.py
jumpstarter/client/lease.py
jumpstarter/client/lease_test.py
jumpstarter/common/__init__.py
jumpstarter/common/condition.py
jumpstarter/common/exceptions.py
jumpstarter/common/grpc.py
jumpstarter/common/importlib.py
jumpstarter/common/importlib_test.py
jumpstarter/common/ipaddr.py
jumpstarter/common/ipaddr_test.py
jumpstarter/common/metadata.py
jumpstarter/common/resources.py
jumpstarter/common/serde.py
jumpstarter/common/storage.py
jumpstarter/common/streams.py
jumpstarter/common/tempfile.py
jumpstarter/common/utils.py
jumpstarter/common/utils_test.py
jumpstarter/config/__init__.py
jumpstarter/config/client.py
jumpstarter/config/client_config_test.py
jumpstarter/config/common.py
jumpstarter/config/env.py
jumpstarter/config/exporter.py
jumpstarter/config/exporter_test.py
jumpstarter/config/grpc.py
jumpstarter/config/shell.py
jumpstarter/config/tls.py
jumpstarter/config/user.py
jumpstarter/config/user_config_test.py
jumpstarter/driver/__init__.py
jumpstarter/driver/base.py
jumpstarter/driver/decorators.py
jumpstarter/driver/decorators_test.py
jumpstarter/exporter/__init__.py
jumpstarter/exporter/exporter.py
jumpstarter/exporter/logging.py
jumpstarter/exporter/session.py
jumpstarter/exporter/session_test.py
jumpstarter/streams/__init__.py
jumpstarter/streams/aiohttp.py
jumpstarter/streams/blocking.py
jumpstarter/streams/common.py
jumpstarter/streams/encoding.py
jumpstarter/streams/encoding_test.py
jumpstarter/streams/metadata.py
jumpstarter/streams/progress.py
jumpstarter/streams/router.py
jumpstarter/utils/__init__.py
jumpstarter/utils/env.py
jumpstarter-0.7.4.dist-info/METADATA
jumpstarter-0.7.4.dist-info/WHEEL
jumpstarter-0.7.4.dist-info/RECORD
