Metadata-Version: 2.4
Name: jumpstarter
Version: 0.7.4
Project-URL: Homepage, https://jumpstarter.dev
Project-URL: source_archive, https://github.com/jumpstarter-dev/repo/archive/c5d38de69eadbb8eb0388bcfe3430a679fff0059.zip
Author-email: Miguel Angel Ajo Pelayo <majopela@redhat.com>, Nick Cao <ncao@redhat.com>, Kirk Brauer <kbrauer@hatci.com>
License-Expression: Apache-2.0
Requires-Python: >=3.11
Requires-Dist: aiohttp>=3.10.5
Requires-Dist: anyio!=4.6.2,>=4.4.0
Requires-Dist: jumpstarter-protocol==0.7.4
Requires-Dist: pydantic-settings>=2.9.1
Requires-Dist: pydantic>=2.8.2
Requires-Dist: pyyaml>=6.0.2
Requires-Dist: rich>=14.0.0
Requires-Dist: tenacity>=8.2.0
Requires-Dist: xdg-base-dirs>=6.0.2
